structured_tutorials/__init__.py
structured_tutorials/cli.py
structured_tutorials/errors.py
structured_tutorials/output.py
structured_tutorials/textwrap.py
structured_tutorials/typing.py
structured_tutorials/utils.py
structured_tutorials/models/__init__.py
structured_tutorials/models/base.py
structured_tutorials/models/parts.py
structured_tutorials/models/tests.py
structured_tutorials/models/tutorial.py
structured_tutorials/models/validators.py
structured_tutorials/runners/__init__.py
structured_tutorials/runners/base.py
structured_tutorials/runners/local.py
structured_tutorials/sphinx/__init__.py
structured_tutorials/sphinx/directives.py
structured_tutorials/sphinx/utils.py
structured_tutorials/templates/alternative_part.rst.template
structured_tutorials/templates/commands_part.rst.template
structured_tutorials/templates/file_part.rst.template
structured_tutorials-0.3.0.dist-info/METADATA
structured_tutorials-0.3.0.dist-info/WHEEL
structured_tutorials-0.3.0.dist-info/entry_points.txt
structured_tutorials-0.3.0.dist-info/licenses/LICENSE
structured_tutorials-0.3.0.dist-info/RECORD
