Metadata-Version: 2.4
Name: structured-tutorials
Version: 0.3.0
Summary: Add your description here
Project-URL: Homepage, https://structured-tutorials.readthedocs.io/
Project-URL: Documentation, https://structured-tutorials.readthedocs.io/
Project-URL: Source, https://github.com/mathiasertl/structured-tutorials
Project-URL: Issues, https://github.com/mathiasertl/structured-tutorials/issues
Project-URL: Changelog, https://structured-tutorials.readthedocs.io/en/latest/changelog.html
License-Expression: MIT
License-File: LICENSE
Classifier: Development Status :: 4 - Beta
Classifier: Framework :: Sphinx :: Extension
Classifier: Intended Audience :: Developers
Classifier: Programming Language :: Python :: 3
Classifier: Programming Language :: Python :: 3 :: Only
Classifier: Programming Language :: Python :: 3.10
Classifier: Programming Language :: Python :: 3.11
Classifier: Programming Language :: Python :: 3.12
Classifier: Programming Language :: Python :: 3.13
Classifier: Programming Language :: Python :: 3.14
Classifier: Topic :: Documentation :: Sphinx
Classifier: Typing :: Typed
Requires-Python: >=3.10
Requires-Dist: colorama>=0.4.6
Requires-Dist: jinja2>=3.1.6
Requires-Dist: pydantic>=2.11.4
Requires-Dist: pyyaml>=6.0.2
Requires-Dist: sphinx-inline-tabs>=2025
Requires-Dist: sphinx>=8.1.0; python_version >= '3.11'
Requires-Dist: sphinx~=8.1.0; python_version < '3.11'
Requires-Dist: termcolor>=3.2.0
Requires-Dist: typing-extensions>=4.6.0; python_version < '3.11'
